wsgi_tools/__init__.py
wsgi_tools/basic_auth.py
wsgi_tools/error.py
wsgi_tools/filtered_parser.py
wsgi_tools/friendly.py
wsgi_tools/parser.py
wsgi_tools/routing.py
wsgi_tools/utils.py
wsgi_tools-0.5.1.dist-info/LICENSE
wsgi_tools-0.5.1.dist-info/METADATA
wsgi_tools-0.5.1.dist-info/WHEEL
wsgi_tools-0.5.1.dist-info/top_level.txt
wsgi_tools-0.5.1.dist-info/RECORD
