Metadata-Version: 2.1
Name: wsgi-tools
Version: 0.5.1
Summary: A collection of WSGI packages.
Home-page: http://wsgi-tools.rtfd.io/
Author: rpkak
License: Apache 2.0
Platform: UNKNOWN
Classifier: Programming Language :: Python
Classifier: Programming Language :: Python :: 3
Classifier: Topic :: Internet :: WWW/HTTP :: WSGI :: Middleware
Classifier: Topic :: Internet :: WWW/HTTP :: WSGI
Classifier: Topic :: Internet :: WWW/HTTP
Classifier: Topic :: Internet
License-File: LICENSE
Provides-Extra: docs
Requires-Dist: Sphinx ; extra == 'docs'
Requires-Dist: furo ; extra == 'docs'
Requires-Dist: myst-parser ; extra == 'docs'
